[
  {
    "id": "100_popular_001",
    "medias": [
      {
        "url": "https://cdn.jsdelivr.net/gh/tramiune/tramiune001_res_wallpaper/resources/100_popular/double_001_0.webp",
        "name": "double_001_0.webp",
        "thumbUrl": "",
        "contentType": "image/webp"
      },
      {
        "url": "https://cdn.jsdelivr.net/gh/tramiune/tramiune001_res_wallpaper/resources/100_popular/double_001_1.webp",
        "name": "double_001_1.webp",
        "thumbUrl": "",
        "contentType": "image/webp"
      }
    ],
    "categoryId": "100_popular",
    "isPremium": true,
    "createdAt": 1766909349,
    "subType": 0,
    "type": 2,
    "coinToUnlock": 0
  },
  {
    "id": "100_popular_001",
    "medias": [
      {
        "url": "https://cdn.jsdelivr.net/gh/tramiune/tramiune001_res_wallpaper/resources/100_popular/days_001_6h.webp",
        "name": "days_001_6h.webp",
        "thumbUrl": "",
        "hour": "06:00",
        "contentType": "image/webp"
      },
      {
        "url": "https://cdn.jsdelivr.net/gh/tramiune/tramiune001_res_wallpaper/resources/100_popular/days_001_12h.webp",
        "name": "days_001_12h.webp",
        "thumbUrl": "",
        "hour": "12:00",
        "contentType": "image/webp"
      },
      {
        "url": "https://cdn.jsdelivr.net/gh/tramiune/tramiune001_res_wallpaper/resources/100_popular/days_001_18h.webp",
        "name": "days_001_18h.webp",
        "thumbUrl": "",
        "hour": "18:00",
        "contentType": "image/webp"
      },
      {
        "url": "https://cdn.jsdelivr.net/gh/tramiune/tramiune001_res_wallpaper/resources/100_popular/days_001_24h.webp",
        "name": "days_001_24h.webp",
        "thumbUrl": "",
        "hour": "24:00",
        "contentType": "image/webp"
      }
    ],
    "categoryId": "100_popular",
    "isPremium": true,
    "createdAt": 1766909350,
    "subType": 0,
    "type": 3,
    "coinToUnlock": 0
  },
  {
    "id": "100_popular_009",
    "medias": [
      {
        "url": "https://cdn.jsdelivr.net/gh/tramiune/tramiune001_res_wallpaper/resources/100_popular/couple_009.webp",
        "name": "couple_009.webp",
        "thumbUrl": "",
        "contentType": "image/webp"
      }
    ],
    "categoryId": "100_popular",
    "isPremium": true,
    "createdAt": 1766909351,
    "subType": 0,
    "type": 4,
    "coinToUnlock": 0
  },
  {
    "id": "100_popular_020",
    "medias": [
      {
        "url": "https://cdn.jsdelivr.net/gh/tramiune/tramiune001_res_wallpaper/resources/100_popular/popular_020.mp4",
        "name": "popular_020.mp4",
        "thumbUrl": "",
        "contentType": "video/mp4"
      },
      {
        "url": "https://cdn.jsdelivr.net/gh/tramiune/tramiune001_res_wallpaper/resources/100_popular/popular_020.webp",
        "name": "popular_020.webp",
        "thumbUrl": "https://cdn.jsdelivr.net/gh/tramiune/tramiune001_res_wallpaper/resources/100_popular/popular_020_preview.webp",
        "contentType": "image/webp"
      }
    ],
    "categoryId": "100_popular",
    "isPremium": true,
    "createdAt": 1766909352,
    "subType": 0,
    "type": 0,
    "coinToUnlock": 0
  }
]